file_resubmit-0.1.0.dist-info/DESCRIPTION.rst
file_resubmit-0.1.0.dist-info/METADATA
file_resubmit-0.1.0.dist-info/RECORD
file_resubmit-0.1.0.dist-info/WHEEL
file_resubmit-0.1.0.dist-info/metadata.json
file_resubmit-0.1.0.dist-info/top_level.txt
resubmit/__init__.py
resubmit/admin.py
resubmit/cache.py
resubmit/widgets.py
