Metadata-Version: 2.0
Name: file-resubmit
Version: 0.1.0
Summary: Keeps submited files when validation errors occur.
Home-page: UNKNOWN
Author: Ilya Shalyapin
Author-email: ishalyapin@gmail.com
License: MIT License
Keywords: django form filefield resubmit
Platform: UNKNOWN
Classifier: Environment :: Web Environment
Classifier: Framework :: Django
Classifier: Intended Audience :: Developers
Classifier: Programming Language :: Python
Classifier: Programming Language :: Python :: 3
Classifier: Programming Language :: Python :: 3.3
Classifier: Programming Language :: Python :: 3.5
Requires: python (>= 3.3)
Requires: django (>= 1.8)
